{
    "KEY_TONE_SUITE" : "钢琴(半音阶)",
    "KEY_TONE_DEFAULT" : "01-G1.aiff",
    "KEY_TONE_NORMAL" : "01-G1.aiff",
    "KEY_TONE_FUNCTION" : "12-D3.aiff",
    "KEY_TONE_TOOL" : "zryj.aiff",
    "KEY_TONE_CANDIDATE" : "29-G5.aiff",

    "Q" : "20-E4.aiff",
    "W" : "21-F4.aiff",
    "E" : "22-G4.aiff",
    "R" : "23-A4.aiff",
    "T" : "24-B4.aiff",
    "Y" : "25-C5.aiff",
    "U" : "26-D5.aiff",
    "I" : "27-E5.aiff",
    "O" : "28-F5.aiff",
    "P" : "29-G5.aiff",
    "P1" : "28-F5.aiff",
    "P2" : "27-E5.aiff",
    "A" : "11-C3.aiff",
    "S" : "12-D3.aiff",
    "D" : "13-E3.aiff",
    "F" : "14-F3.aiff",
    "G" : "15-G3.aiff",
    "H" : "16-A3.aiff",
    "J" : "17-B3.aiff",
    "K" : "18-C4.aiff",
    "L" : "19-D4.aiff",
    "L1" : "20-E4.aiff",
    "L2" : "21-F4.aiff",
    "L3" : "22-G4.aiff",
    "Z" : "04-C2.aiff",
    "X" : "05-D2.aiff",
    "C" : "06-E2.aiff",
    "V" : "07-F2.aiff",
    "B" : "08-G2.aiff",
    "N" : "09-A2.aiff",
    "M" : "10-B2.aiff",
    "M1" : "11-C3.aiff",
    "M2" : "12-D3.aiff",
    "M3" : "13-E3.aiff",
    "M4" : "14-F3.aiff",
    "M5" : "15-G3.aiff",
    "Z1" : "20-E4.aiff",
    "X2" : "21-F4.aiff",
    "C1" : "22-G4.aiff",
    "V1" : "23-A4.aiff",
    "B1" : "24-B4.aiff",
    "N1" : "25-C5.aiff",
    "M6" : "26-D5.aiff",
    "M7" : "27-E5.aiff",
    "M8" : "28-F5.aiff",
    "M9" : "29-G5.aiff",
    "BackwardDelete" : "14-F3.aiff",
    "Globe" : "23-A4.aiff",
    "Numeric" : "24-B4.aiff",
    "Symbols" : "25-C5.aiff",
    "Shift" : "26-D5.aiff",
    "Default" : "14-F3.aiff",
    "Preview" : "zryj.aiff",
    "ToolbarSogouLogo" : "zryj.aiff",
    "ToolbarEmojiIcon" : "11-C3.aiff",
    "ToolbarPassword" : "12-D3.aiff",
    "ToolbarPasswordClip" : "13-E3.aiff",
    "ToolbarEmojiExpand" : "12-D3.aiff",
    "ToolbarGraphic" : "12-D3.aiff",
    "Space" : "14-F3.aiff",
    "ClickDelete" : "14-F3.aiff",
    "LongPressDelete" : "Silence",
    "Send" : "zryj.aiff",
    "Return" : "zryj.aiff",
    "Next" : "zryj.aiff",
    "Go" : "zryj.aiff",
    "Search" : "zryj.aiff",
    "DefReturn" : "zryj.aiff"
}
